publishable_package_02/__init__.py
publishable_package_02/add.py
publishable_package_02/app.py
publishable_package_02/cal.py
publishable_package_02/div.py
publishable_package_02/mul.py
publishable_package_02/sub.py
publishable_package_02-0.1.0.dist-info/METADATA
publishable_package_02-0.1.0.dist-info/WHEEL
publishable_package_02-0.1.0.dist-info/entry_points.txt
publishable_package_02-0.1.0.dist-info/RECORD
