Metadata-Version: 2.4
Name: publishable-package_02
Version: 0.1.0
Summary: Add your description here
Author-email: "M.Anees" <manees7865@gmail.com>
Requires-Python: >=3.12
Requires-Dist: rich>=14.0.0
